src/__init__.py
src/get_gender.py
src/keras_model.h5
gender_based-0.3.0.dist-info/METADATA
gender_based-0.3.0.dist-info/WHEEL
gender_based-0.3.0.dist-info/RECORD
