Metadata-Version: 2.1
Name: gender-based
Version: 0.3.0
Summary: Library containing model to find the gender of a speaker through audio file
Author: Priya-begur
Author-email: priya@shavik.ai
Requires-Python: >=3.11,<4.0
Classifier: Programming Language :: Python :: 3
Classifier: Programming Language :: Python :: 3.11
Classifier: Programming Language :: Python :: 3.12
Requires-Dist: keras (>=2.7.0,<3.0.0)
Requires-Dist: librosa (>=0.8.1,<0.9.0)
Requires-Dist: requests (>=2.31.0,<3.0.0)
Requires-Dist: tensorflow (>=2.7.0,<3.0.0)
